README.md
setup.py
istype/__init__.py
istype/g.py
istype.egg-info/PKG-INFO
istype.egg-info/SOURCES.txt
istype.egg-info/dependency_links.txt
istype.egg-info/not-zip-safe
istype.egg-info/top_level.txt
istype/internal/__init__.py
istype/internal/any.py
istype/internal/common.py
istype/internal/generic_alias.py
istype/internal/generic_alias_py36.py
istype/internal/tuple.py
istype/internal/typevar.py