Metadata-Version: 1.0
Name: istype
Version: 0.2.0
Summary: UNKNOWN
Home-page: https://github.com/Cologler/istype-python
Author: cologler
Author-email: skyoflw@gmail.com
License: MIT
Keywords: python,typing
Platform: UNKNOWN
